_evoke_cpp.cpython-314-x86_64-linux-gnu.so
_orca_cpp.cpython-314-x86_64-linux-gnu.so
orbitsi/__init__.py
orbitsi/main.py
orbitsi/utils.py
orbitsi/orbit/__init__.py
orbitsi/orbit/evoke.py
orbitsi/orbit/orbit_converter.py
orbitsi/orbit/orca.py
orbitsi/search/__init__.py
orbitsi/search/filtering.py
orbitsi/search/ordering.py
orbitsi/search/searching.py
orbitsi-0.1.2.dist-info/METADATA
orbitsi-0.1.2.dist-info/WHEEL
orbitsi-0.1.2.dist-info/entry_points.txt
orbitsi-0.1.2.dist-info/top_level.txt
orbitsi-0.1.2.dist-info/RECORD
orbitsi-0.1.2.dist-info/licenses/LICENSE
