Metadata-Version: 2.4
Name: orbitsi
Version: 0.1.2
Summary: OrbitSI: An Orbit-based Algorithm for the Subgraph Isomorphism Search Problem
Author-email: Syed Ibtisam Tauhidi <stauhidi01@qub.ac.uk>
License: Apache-2.0
Project-URL: Homepage, https://hpdc-gitlab.eeecs.qub.ac.uk/sitauhidi/orbitsi-nx
Project-URL: Documentation, https://hpdc-gitlab.eeecs.qub.ac.uk/sitauhidi/orbitsi-nx/-/wikis/home
Project-URL: Source, https://hpdc-gitlab.eeecs.qub.ac.uk/sitauhidi/orbitsi-nx
Keywords: graphlets,orbits,subgraph isomorphism,EVOKE,ORCA
Classifier: Programming Language :: Python :: 3
Classifier: License :: OSI Approved :: Apache Software License
Classifier: Operating System :: OS Independent
Requires-Python: >=3.8
License-File: LICENSE
Requires-Dist: networkx
Requires-Dist: numpy
Requires-Dist: pybind11
Dynamic: license-file
